LICENSE
MANIFEST.in
README.md
pyproject.toml
setup.py
CO_conversion_factor/__init__.py
CO_conversion_factor/alphaCO.py
CO_conversion_factor/metallicity.py
CO_conversion_factor.egg-info/PKG-INFO
CO_conversion_factor.egg-info/SOURCES.txt
CO_conversion_factor.egg-info/dependency_links.txt
CO_conversion_factor.egg-info/requires.txt
CO_conversion_factor.egg-info/top_level.txt