Metadata-Version: 2.1
Name: CO_conversion_factor
Version: 1.0
Summary: Python implementation of existing CO-to-H2 conversion factor prescriptions in the literature.
Author-email: Jiayi Sun <jysun.princeton@gmail.com>
License: GPL-3.0 License
Project-URL: homepage, https://github.com/astrojysun/COConversionFactor
License-File: LICENSE
Requires-Dist: numpy
Requires-Dist: scipy
Requires-Dist: astropy
